podsearch/__init__.py
podsearch/http.py
podsearch/searcher.py
podsearch-0.3.1.dist-info/LICENSE
podsearch-0.3.1.dist-info/WHEEL
podsearch-0.3.1.dist-info/METADATA
podsearch-0.3.1.dist-info/RECORD
