Metadata-Version: 2.1
Name: podsearch
Version: 0.3.1
Summary: Let's find some podcasts!
Home-page: https://github.com/nalgeon/podsearch-py
Author: Anton Zhiyanov
Author-email: m@antonz.ru
Requires-Python: >=3.7
Classifier: License :: OSI Approved :: MIT License
Classifier: Programming Language :: Python :: 3
